{
    "id": "c900363f-8e6f-4e85-b300-402328c909d6",
    "title": "Wizard's Isle",
    "slug": null,
    "state": "private",
    "isWip": null,
    "isDraft": null,
    "entityClass": "Marker",
    "icon": "fa-solid fa-location-dot",
    "url": null,
    "subscribergroups": [
        {
            "id": "b153b24e-2dcf-4d2c-8615-0c24bdc06d16",
            "title": "Haven Irregulars",
            "slug": null,
            "state": null,
            "entityClass": "SubscriberGroup",
            "icon": null,
            "url": null,
            "subscribergroups": []
        }
    ],
    "folderId": null,
    "tags": "",
    "updateDate": null,
    "description": "Off the north end of Trade Island, this was once used by smugglers moving good upreiver.[br]Map Ref: TD (J14)",
    "position": null,
    "htmlMarker": null,
    "seeded": null,
    "creationDate": null,
    "isDeleted": null,
    "type": null,
    "isDirectLink": false,
    "isDraggable": false,
    "labelTitle": null,
    "labelType": "label-default",
    "className": null,
    "geoX": 2994,
    "geoY": 4276,
    "geoZ": null,
    "polygonPoints": null,
    "circleRadius": null,
    "linePoints": null,
    "lineColor": null,
    "lineWeight": null,
    "lineOpacity": null,
    "lineDash": null,
    "colorOutline": null,
    "colorFill": null,
    "opacityOutline": null,
    "opacityFill": null,
    "isEditable": true,
    "success": true
}